README
setup.py
pyssp/__init__.py
pyssp/distance.py
pyssp/feature.py
pyssp/util.py
pyssp/voice_enhancement.py
pyssp.egg-info/PKG-INFO
pyssp.egg-info/SOURCES.txt
pyssp.egg-info/dependency_links.txt
pyssp.egg-info/namespace_packages.txt
pyssp.egg-info/requires.txt
pyssp.egg-info/top_level.txt
pyssp/noise_estimation/__init__.py
pyssp/noise_estimation/minimum_statistics.py
pyssp/noise_estimation/mmse_estimator.py
pyssp/noise_estimation/ms_sample.py
pyssp/noise_estimation/ra_estimator.py
pyssp/vad/__init__.py
pyssp/vad/ltsd.py
pyssp/vad/par.py