Metadata-Version: 1.1
Name: pyssp
Version: 0.1.9.5
Summary: python speech signal processing library for education
Home-page: https://github.com/shunsukeaihara/pyssp
Author: Shunsuke Aihara
Author-email: s.aihara@gmail.scom
License: The MIT License
Keywords: scipy,speech processing
Platform: UNKNOWN
Classifier: Programming Language :: Python
Classifier: Topic :: Scientific/Engineering
Classifier: Intended Audience :: Science/Research
